cachecache/CONFIG.py
cachecache/__init__.py
cachecache/cachecache.py
cachecache/utils.py
cachecache-0.2.2.dist-info/LICENSE.md
cachecache-0.2.2.dist-info/METADATA
cachecache-0.2.2.dist-info/WHEEL
cachecache-0.2.2.dist-info/top_level.txt
cachecache-0.2.2.dist-info/RECORD
