Metadata-Version: 2.1
Name: cachecache
Version: 0.2.2
Summary: Python package for easy function caching, allowing users to customize cache behavior at call-time.
Home-page: https://github.com/m-beau/cachecache
Author: Maxime Beau
Author-email: m.beau047@gmail.com
License: GPL-3.0
Classifier: Development Status :: 3 - Alpha
Classifier: Intended Audience :: Developers
Classifier: License :: OSI Approved :: GNU General Public License v3 (GPLv3)
Classifier: Programming Language :: Python :: 3
Classifier: Programming Language :: Python :: 3.6
Classifier: Programming Language :: Python :: 3.7
Classifier: Programming Language :: Python :: 3.8
Classifier: Programming Language :: Python :: 3.9
Requires-Python: >=3.6
License-File: LICENSE.md
Requires-Dist: joblib >=1.4
Requires-Dist: psutil
